Metadata-Version: 1.1
Name: package-archetype
Version: 0.4
Summary: A simple lib that prints out hello world
Home-page: https://github.com/DEV3L/python-package-archetype
Author: Justin Beall
Author-email: jus.beall@gmail.com
License: UNKNOWN
Download-URL: https://github.com/DEV3L/python-package-archetype/tarball/0.4
Keywords: dev3l,archetype,pypi,package
Platform: UNKNOWN
Classifier: Environment :: Console
Classifier: Intended Audience :: Developers
Classifier: License :: OSI Approved :: MIT License
Classifier: Operating System :: OS Independent
Classifier: Programming Language :: Python
Classifier: Programming Language :: Python :: 2
Classifier: Programming Language :: Python :: 3
Classifier: Topic :: Software Development :: Libraries :: Python Modules
